djpress_publish_bluesky/__init__.py
djpress_publish_bluesky/plugin.py
djpress_publish_bluesky-1.1.0.dist-info/METADATA
djpress_publish_bluesky-1.1.0.dist-info/WHEEL
djpress_publish_bluesky-1.1.0.dist-info/entry_points.txt
djpress_publish_bluesky-1.1.0.dist-info/RECORD
