Metadata-Version: 2.4
Name: djpress-publish-bluesky
Version: 1.1.0
Summary: A plugin for DJ Press that publishes new posts to Bluesky.
Author-email: Stuart Maxwell <stuart@amanzi.nz>
Requires-Python: >=3.10
Requires-Dist: djpress>=0.20
Requires-Dist: httpx>=0.28.0
